Metadata-Version: 1.0
Name: mypythonpiptest
Version: 0.2
Summary: my first python pip
Home-page: https://github.com/wangzishuo111/mypythonpiptest.git
Author: wangzishuo
Author-email: wzs_wangzishuo@163.com
License: UNKNOWN
Platform: UNKNOWN
